QAnglesKit/__init__.py
QAnglesKit/auth.py
QAnglesKit/base_api.py
QAnglesKit/client.py
QAnglesKit/config.json
QAnglesKit/cudaq.py
QAnglesKit/dashboard.py
QAnglesKit/lqm.py
QAnglesKit/projects.py
QAnglesKit/qcircuit.py
QAnglesKit/simulations.py
QAnglesKit/tools.py
QuantumJobClient/__init__.py
QuantumJobClient/client.py
QAnglesKit-0.0.4.77.dist-info/METADATA
QAnglesKit-0.0.4.77.dist-info/WHEEL
QAnglesKit-0.0.4.77.dist-info/entry_points.txt
QAnglesKit-0.0.4.77.dist-info/top_level.txt
QAnglesKit-0.0.4.77.dist-info/RECORD
