Metadata-Version: 2.2
Name: QAnglesKit
Version: 0.0.4.77
Summary: QAngles Quantum Solution SDK
Author: saipranay
Author-email: info@cloudangles.com
Classifier: Programming Language :: Python :: 3
Classifier: License :: OSI Approved :: MIT License
Classifier: Operating System :: OS Independent
Requires-Python: >=3.7
Requires-Dist: requests
Requires-Dist: pillow
Requires-Dist: IPython
Dynamic: author
Dynamic: author-email
Dynamic: classifier
Dynamic: description
Dynamic: description-content-type
Dynamic: requires-dist
Dynamic: requires-python
Dynamic: summary
